LICENSE.txt
README.md
setup.cfg
setup.py
mongo_mango/DB.py
mongo_mango/DbObject.py
mongo_mango/Errors.py
mongo_mango/Schema.py
mongo_mango/__init__.py
mongo_mango.egg-info/PKG-INFO
mongo_mango.egg-info/SOURCES.txt
mongo_mango.egg-info/dependency_links.txt
mongo_mango.egg-info/requires.txt
mongo_mango.egg-info/top_level.txt