Metadata-Version: 2.4
Name: mongo_mango
Version: 0.1
Summary: Make your life easy with a Mongoose inspired Schema for Python and pymongo
Home-page: https://github.com/shubhamakshit/easy_db
Download-URL: https://github.com/user/reponame/archive/v_01.tar.gz
Author: Akshit Shubham
Author-email: akshitshubhammas@gmail.com
License: MIT
Keywords: SOME,MEANINGFULL,KEYWORDS
Classifier: Development Status :: 3 - Alpha
Classifier: Intended Audience :: Developers
Classifier: Topic :: Software Development :: Build Tools
Classifier: License :: OSI Approved :: MIT License
Classifier: Programming Language :: Python :: 3
Classifier: Programming Language :: Python :: 3.4
Classifier: Programming Language :: Python :: 3.5
Classifier: Programming Language :: Python :: 3.6
License-File: LICENSE.txt
Requires-Dist: pymongo
Dynamic: author
Dynamic: author-email
Dynamic: classifier
Dynamic: download-url
Dynamic: home-page
Dynamic: keywords
Dynamic: license
Dynamic: license-file
Dynamic: requires-dist
Dynamic: summary
